smartethan/__init__.py
smartethan/checker.py
smartethan-0.1.1.dist-info/METADATA
smartethan-0.1.1.dist-info/WHEEL
smartethan-0.1.1.dist-info/RECORD
